aldy/__init__.py
aldy/__main__.py
aldy/cn.py
aldy/common.py
aldy/coverage.py
aldy/diplotype.py
aldy/gene.py
aldy/genotype.py
aldy/lpinterface.py
aldy/major.py
aldy/minor.py
aldy/profile.py
aldy/query.py
aldy/sam.py
aldy/solutions.py
aldy/version.py
aldy/resources/LICENSE.rst
aldy/resources/__init__.py
aldy/resources/genes/__init__.py
aldy/resources/genes/cftr.yml
aldy/resources/genes/comt.yml
aldy/resources/genes/cyp1a1.yml
aldy/resources/genes/cyp1a2.yml
aldy/resources/genes/cyp2a13.yml
aldy/resources/genes/cyp2a6.yml
aldy/resources/genes/cyp2b6.yml
aldy/resources/genes/cyp2c19.yml
aldy/resources/genes/cyp2c8.yml
aldy/resources/genes/cyp2c9.yml
aldy/resources/genes/cyp2d6.yml
aldy/resources/genes/cyp2e1.yml
aldy/resources/genes/cyp2f1.yml
aldy/resources/genes/cyp2j2.yml
aldy/resources/genes/cyp2r1.yml
aldy/resources/genes/cyp2s1.yml
aldy/resources/genes/cyp2w1.yml
aldy/resources/genes/cyp3a4.yml
aldy/resources/genes/cyp3a43.yml
aldy/resources/genes/cyp3a5.yml
aldy/resources/genes/cyp3a7.yml
aldy/resources/genes/cyp4f2.yml
aldy/resources/genes/dpyd.yml
aldy/resources/genes/g6pd.yml
aldy/resources/genes/gstm1.yml
aldy/resources/genes/gstp1.yml
aldy/resources/genes/ifnl3.yml
aldy/resources/genes/nat1.yml
aldy/resources/genes/nat2.yml
aldy/resources/genes/nudt15.yml
aldy/resources/genes/slco1b1.yml
aldy/resources/genes/tpmt.yml
aldy/resources/genes/ugt1a1.yml
aldy/resources/genes/ugt2b7.yml
aldy/resources/genes/vkorc1.yml
aldy/resources/profiles/10x.yml
aldy/resources/profiles/__init__.py
aldy/resources/profiles/illumina.yml
aldy/resources/profiles/pacbio-hifi-targeted-twist.yml
aldy/resources/profiles/pacbio-hifi-targeted.yml
aldy/resources/profiles/pgx1.yml
aldy/resources/profiles/pgx2.yml
aldy/resources/profiles/pgx3.yml
aldy/tests/__init__.py
aldy/tests/conftest.py
aldy/tests/test_cn_real.py
aldy/tests/test_cn_synthetic.py
aldy/tests/test_diplotype_real.py
aldy/tests/test_diplotype_synthetic.py
aldy/tests/test_full.py
aldy/tests/test_gene.py
aldy-4.1.dist-info/LICENSE.rst
aldy-4.1.dist-info/METADATA
aldy-4.1.dist-info/WHEEL
aldy-4.1.dist-info/entry_points.txt
aldy-4.1.dist-info/top_level.txt
aldy-4.1.dist-info/RECORD
