Metadata-Version: 2.1
Name: aldy
Version: 4.1
Summary: A tool for allelic decomposition (haplotype reconstruction) and exact genotyping of highly polymorphic and structurally variant genes
Home-page: http://aldy.csail.mit.edu/
Author: Ibrahim Numanagić
Author-email: inumanag@mit.edu
License: Aldy/IURTC License. Free for academic/non-commercial use.
Download-URL: https://github.com/inumanag/aldy/tarball/master
Keywords: cyp2d6,adme,genotyping,illumina,pgrnseq,getrm,allele
Platform: UNKNOWN
Requires-Dist: pyyaml
Requires-Dist: logbook
Requires-Dist: pysam
Requires-Dist: pytest
Requires-Dist: ortools
Requires-Dist: natsort
Requires-Dist: mappy
Requires-Dist: indelpost
